peartree/__init__.py
peartree/__version__.py
peartree/convert.py
peartree/graph.py
peartree/graph_tool.py
peartree/parallel.py
peartree/paths.py
peartree/plot.py
peartree/settings.py
peartree/summarizer.py
peartree/synthetic.py
peartree/toolkit.py
peartree/utilities.py
peartree-0.6.4.dist-info/LICENSE
peartree-0.6.4.dist-info/METADATA
peartree-0.6.4.dist-info/WHEEL
peartree-0.6.4.dist-info/top_level.txt
peartree-0.6.4.dist-info/RECORD
