Metadata-Version: 2.1
Name: peartree
Version: 0.6.4
Summary: peartree is a library for converting GTFS to directed graphs.
Home-page: https://github.com/kuanb/peartree
Author: Kuan Butts
Author-email: kuanbutts@gmail.com
License: MIT license
Keywords: peartree
Platform: UNKNOWN
Classifier: Intended Audience :: Developers
Classifier: License :: OSI Approved :: MIT License
Classifier: Natural Language :: English
Classifier: Programming Language :: Python :: 3.6
Requires-Dist: fiona (>=1.6.1)
Requires-Dist: geopandas (>=0.4.0)
Requires-Dist: networkx (>=2.0)
Requires-Dist: numpy (>=1.18.4)
Requires-Dist: pandas (>=1.0.3)
Requires-Dist: partridge (>=1.0.0)
